{
	"logLevel": 1,
	"urlSettings": [],
	"hiddenSettings": {},
	"expandStatus": {
		"section_settings": true
	},
	"displayHiddenSettings": true,
	"whiteList": "",
	"sessionWhiteList": "",
	"blackList": "",
	"blockMode": "fake",
	"protectedCanvasPart": "input",
	"minFakeSize": 10,
	"maxFakeSize": 0,
	"rng": "persistent",
	"protectedAPIFeatures": {},
	"useCanvasCache": true,
	"ignoreFrequentColors": 3,
	"minColors": 3,
	"fakeAlphaChannel": false,
	"webGLVendor": "",
	"webGLRenderer": "",
	"webGLUnmaskedVendor": "",
	"webGLUnmaskedRenderer": "",
	"persistentRndStorage": "{}",
	"persistentIncognitoRndStorage": "{}",
	"storePersistentRnd": false,
	"persistentRndClearIntervalValue": 7,
	"persistentRndClearIntervalUnit": "days",
	"lastPersistentRndClearing": 1764367635686,
	"sharePersistentRndBetweenDomains": false,
	"askOnlyOnce": "individual",
	"askDenyMode": "block",
	"showCanvasWhileAsking": true,
	"showNotifications": true,
	"highlightPageAction": "none",
	"highlightBrowserAction": "color",
	"displayBadge": true,
	"storeNotificationData": false,
	"storeImageForInspection": false,
	"ignoreList": "",
	"ignoredAPIs": {},
	"showCallingFile": false,
	"showCompleteCallingStack": false,
	"enableStackList": false,
	"stackList": "",
	"protectAudio": true,
	"audioFakeRate": "0.1%",
	"audioNoiseLevel": "low",
	"useAudioCache": true,
	"audioUseFixedIndices": true,
	"audioFixedIndices": "9",
	"historyLengthThreshold": 2,
	"protectWindow": true,
	"allowWindowNameInFrames": true,
	"protectDOMRect": true,
	"domRectIntegerFactor": 4,
	"protectSVG": true,
	"protectTextMetrics": true,
	"blockDataURLs": true,
	"protectNavigator": false,
	"navigatorDetails": {},
	"protectScreen": true,
	"screenSize": "",
	"fakeMinimalScreenSize": false,
	"displayAdvancedSettings": true,
	"displayDescriptions": true,
	"theme": "auto",
	"showPresetsOnInstallation": true,
	"dontShowOptionsOnUpdate": false,
	"disruptSessionOnUpdate": false,
	"updatePending": false,
	"isStillDefault": false,
	"storageVersion": 1
}